codepost_powertools/__init__.py
codepost_powertools/__main__.py
codepost_powertools/_utils/__init__.py
codepost_powertools/_utils/_logger.py
codepost_powertools/_utils/cli_utils.py
codepost_powertools/_utils/file_io.py
codepost_powertools/_utils/handle_errors.py
codepost_powertools/config.py
codepost_powertools/grading/__init__.py
codepost_powertools/grading/_cli_group.py
codepost_powertools/grading/ids.py
codepost_powertools/info.py
codepost_powertools/utils/__init__.py
codepost_powertools/utils/codepost_utils.py
codepost_powertools/utils/cptypes.py
codepost_powertools/utils/types.py
codepost_powertools-0.1.0.dist-info/LICENSE
codepost_powertools-0.1.0.dist-info/WHEEL
codepost_powertools-0.1.0.dist-info/entry_points.txt
codepost_powertools-0.1.0.dist-info/METADATA
codepost_powertools-0.1.0.dist-info/RECORD
