Metadata-Version: 2.1
Name: codepost-powertools
Version: 0.1.0
Summary: Some helpful codePost tools to aid with grading flow.
Home-page: https://codepost-powertools.readthedocs.io/en/latest/
License: MIT
Keywords: codepost,tools,powertools,Google Sheets,Princeton,COS126
Author: Joseph Lou
Author-email: jdlou@princeton.edu
Requires-Python: >=3.7.2,<4.0.0
Classifier: License :: OSI Approved :: MIT License
Classifier: Programming Language :: Python :: 3
Classifier: Programming Language :: Python :: 3.8
Classifier: Programming Language :: Python :: 3.9
Classifier: Programming Language :: Python :: 3.10
Classifier: Programming Language :: Python :: 3.11
Classifier: Programming Language :: Python :: 3.10
Classifier: Programming Language :: Python :: 3.11
Classifier: Programming Language :: Python :: 3.7
Classifier: Programming Language :: Python :: 3.8
Classifier: Programming Language :: Python :: 3.9
Classifier: Topic :: Education
Classifier: Topic :: Software Development :: Libraries :: Python Modules
Classifier: Typing :: Typed
Requires-Dist: click (>=8.1.3,<9.0.0)
Requires-Dist: codepost (>=0.2.29,<0.3.0)
Requires-Dist: comma (>=0.5.4,<0.6.0)
Requires-Dist: importlib-metadata (>=1.0) ; python_version < "3.8"
Requires-Dist: loguru (>=0.6.0,<0.7.0)
Project-URL: Documentation, https://codepost-powertools.readthedocs.io/en/latest/
Project-URL: Repository, https://github.com/PrincetonCS-UCA/codepost-powertools
